BeautifulTerminal/__init__.py
BeautifulTerminal/terminal.py
beautiful_terminal-1.0.1.dist-info/licenses/LICENSE
beautiful_terminal-1.0.1.dist-info/METADATA
beautiful_terminal-1.0.1.dist-info/WHEEL
beautiful_terminal-1.0.1.dist-info/top_level.txt
beautiful_terminal-1.0.1.dist-info/RECORD
