Metadata-Version: 2.4
Name: beautiful-terminal
Version: 1.0.1
Summary: A Python library that automatically beautifies terminal output by adding colors based on message content.
Home-page: https://github.com/StarByteGames/beautiful-terminal
Author: DevStarByte
Author-email: 
License: MIT
Keywords: terminal color console logging beautify
Classifier: Development Status :: 5 - Production/Stable
Classifier: Intended Audience :: Developers
Classifier: Topic :: Software Development :: Libraries
Classifier: Topic :: Utilities
Classifier: License :: OSI Approved :: MIT License
Classifier: Operating System :: OS Independent
Classifier: Programming Language :: Python :: 3
Classifier: Programming Language :: Python :: 3.6
Classifier: Programming Language :: Python :: 3.7
Classifier: Programming Language :: Python :: 3.8
Classifier: Programming Language :: Python :: 3.9
Classifier: Programming Language :: Python :: 3.10
Requires-Python: >=3.6
License-File: LICENSE
Provides-Extra: version-check
Requires-Dist: requests; extra == "version-check"
Requires-Dist: setuptools; extra == "version-check"
Dynamic: author
Dynamic: classifier
Dynamic: description
Dynamic: description-content-type
Dynamic: home-page
Dynamic: keywords
Dynamic: license
Dynamic: license-file
Dynamic: provides-extra
Dynamic: requires-python
Dynamic: summary
